holviapi/__init__.py
holviapi/categories.py
holviapi/checkout.py
holviapi/connection.py
holviapi/contacts.py
holviapi/invoicing.py
holviapi/products.py
holviapi/utils.py
holviapi/errors/__init__.py
holviapi/tests/__init__.py
holviapi/tests/fixtures.py
holviapi/tests/test_api_dangerous.py
holviapi/tests/test_api_idempotent.py
holviapi/tests/test_barcode.py
holviapi/tests/test_refnos.py
holviapi-0.6.20190131.dist-info/LICENSE
holviapi-0.6.20190131.dist-info/METADATA
holviapi-0.6.20190131.dist-info/WHEEL
holviapi-0.6.20190131.dist-info/top_level.txt
holviapi-0.6.20190131.dist-info/RECORD
