Metadata-Version: 2.1
Name: holviapi
Version: 0.6.20190131
Summary: Implement Pythonic wrappers for Holvi JSON-REST API
Home-page: https://github.com/rambo/python-holviapi
Author: Eero "rambo" af Heurlin
Author-email: rambo@iki.fi
License: MIT
Platform: UNKNOWN
Requires-Dist: six (==1.12.0)
Requires-Dist: future (==0.17.1)
Requires-Dist: requests (==2.21.0)
Requires-Dist: requests-cache (==0.4.13)
Requires-Dist: python-dateutil (==2.7.5)
